linux_workload_execution/__init__.py
linux_workload_execution/__main__.py
linux_workload_execution/activation.py
linux_workload_execution-1.0.10.dist-info/LICENSE
linux_workload_execution-1.0.10.dist-info/METADATA
linux_workload_execution-1.0.10.dist-info/WHEEL
linux_workload_execution-1.0.10.dist-info/top_level.txt
linux_workload_execution-1.0.10.dist-info/RECORD
