Metadata-Version: 2.2
Name: linux_workload_execution
Version: 1.0.10
Summary: linux_workload_execution is a Python package designed to take details like, lpar, ipaddress, script directory and script command as the input, and perform below activities
Author-email: Girija <girija.golla@ibm.com>, Sri Vaishnavi <sriva011@in.ibm.com>
Classifier: Programming Language :: Python :: 3
Classifier: License :: OSI Approved :: MIT License
Classifier: Operating System :: OS Independent
Requires-Python: >=3.8
License-File: LICENSE
Requires-Dist: gitdb>=4.0.12
Requires-Dist: GitPython>=3.1.44
Requires-Dist: pytest>=8.3.4
Requires-Dist: paramiko>=3.5.1
Requires-Dist: requests>=2.32.3
Requires-Dist: setuptools>=75.8.0
Requires-Dist: zhmccli>=1.12.0
Requires-Dist: twine>=6.1.0
Requires-Dist: build>=1.2.2
Requires-Dist: pipreqs>=0.4.13
